sempyver/__init__.py
sempyver/__main__.py
sempyver/_version.py
sempyver/cli_application/__init__.py
sempyver/cli_application/cli_app.py
sempyver/cli_application/modules/__init__.py
sempyver/cli_application/modules/changelog_generator.py
sempyver/cli_application/modules/changeset.py
sempyver/cli_application/modules/commit.py
sempyver/cli_application/utilities/__init__.py
sempyver/cli_application/utilities/tags_for_change.py
sempyver/cli_application/utilities/theme.py
sempyver/helpers/__init__.py
sempyver/helpers/cache_generator.py
sempyver/helpers/toml_reader.py
sempyver/helpers/update_version.py
sempyver-0.1.0.dist-info/LICENSE
sempyver-0.1.0.dist-info/METADATA
sempyver-0.1.0.dist-info/WHEEL
sempyver-0.1.0.dist-info/entry_points.txt
sempyver-0.1.0.dist-info/top_level.txt
sempyver-0.1.0.dist-info/RECORD
