Metadata-Version: 2.1
Name: sempyver
Version: 0.1.0
Summary: Tool for teams to manage the CHANGELOG given a list of different changes.
Home-page: 
Author: Ricardo Leal
Author-email: ricardo.lealpz@gmail.com
Maintainer: Ricardo Leal
Maintainer-email: ricardo.lealpz@gmail.com
License-File: LICENSE
Requires-Dist: click (~=8.1)
Requires-Dist: inquirer (~=3.1)
Requires-Dist: colorama (==0.4.6)
Requires-Dist: faker (~=17.6)
